{"account_holder_address": "Z55 B193 F17 ST757\nDOHADOHA-QATAR, DOHA,\nQATAR", "account_holder_name": "KHALED OMAR HAZZAM.", "account_number": "0227-0026758-001-0010-000", "bank_name": "DOHA BANK", "email": "control.pa555@gmail.com", "statement_period_end_date": "31/07/2023", "statement_period_start_date": "01/05/2023", "transactions": [{"balance": 7372.89, "credit_amount": 0.0, "date": "01/05/2023", "debit_amount": 3006.13, "details": "CREDIT CARD PAYMENT (A.R) - 4342#2121"}, {"balance": 6342.89, "credit_amount": 0.0, "date": "01/05/2023", "debit_amount": 1030.0, "details": "PURCHASE - UNIVERSITY OF DOHA TESDOHA QA 00289999000501051933 000001038002 0501 012900#470"}, {"balance": 6290.81, "credit_amount": 0.0, "date": "01/05/2023", "debit_amount": 52.08, "details": "PURCHASE - AL MEERA SAILIYA NORTDOHA QA 0028999900 0501141129 000001253019 0501 005526#470"}, {"balance": 6250.81, "credit_amount": 0.0, "date": "01/05/2023", "debit_amount": 40.0, "details": "PURCHASE - DOHA MODERN BAKERIES DOHDOHA QA 0028999900 0501143639 312114590359 0501 009488#470"}, {"balance": 6169.81, "credit_amount": 0.0, "date": "02/05/2023", "debit_amount": 81.0, "details": "PURCHASE - ALMEERA AL SAILIYA MARDOHA QA 0028999900 0502080930 000001113013 0502 029408#470"}, {"balance": 10169.81, "credit_amount": 4000.0, "date": "02/05/2023", "debit_amount": 0.0, "details": "Q-MONTHLY SALARY- SIF13291801BBQ202305011020-28-2-METAL PALACE FOR ALUMINUM AND METAL#996"}, {"balance": 10269.81, "credit_amount": 100.0, "date": "03/05/2023", "debit_amount": 0.0, "details": "QATCH-BILL SETT - FT231230K0QS-5-AHMED AHMED IDRISS#1439"}, {"balance": 10176.81, "credit_amount": 0.0, "date": "07/05/2023", "debit_amount": 93.0, "details": "PURCHASE - ALMEERA AL SAILIYA MARDOHA QA 00289999000505093845 000001818016 0505 030498#470"}, {"balance": 10143.81, "credit_amount": 0.0, "date": "07/05/2023", "debit_amount": 33.0, "details": "PURCHASE - ROMANA HYPERMARKET SALDOHA QA 0028999900 0505102143 000001125031 0505 002641#470"}, {"balance": 10093.81, "credit_amount": 0.0, "date": "07/05/2023", "debit_amount": 50.0, "details": "PURCHASE - WOQOD AL SALILIYAPS DOHA QA 0028999900 0506125802 000001451006 0506 024876#470"}, {"balance": 10008.81, "credit_amount": 0.0, "date": "07/05/2023", "debit_amount": 85.0, "details": "PURCHASE - ALI INTL TRDG. DOHA QA 0050999900 0506132919 312613266682 0506 266682#470"}, {"balance": 10002.81, "credit_amount": 0.0, "date": "07/05/2023", "debit_amount": 6.0, "details": "PURCHASE - ALI INTL TRDG. DOHA QA 0050999900 0506133920 312613267804 0506 267804#470"}, {"balance": 9902.81, "credit_amount": 0.0, "date": "07/05/2023", "debit_amount": 100.0, "details": "PURCHASE - WOQOD AL SALILIYAPS DOHA QA 0028999900 0506141315 000001451030 0506 002478#470"}, {"balance": 9862.81, "credit_amount": 0.0, "date": "10/05/2023", "debit_amount": 40.0, "details": "PURCHASE-WOQOD AL SALILIYAPS DOHA QA 0028999900 0510053443 000001436034 0510 012742#470"}, {"balance": 9762.81, "credit_amount": 0.0, "date": "14/05/2023", "debit_amount": 100.0, "details": "PURCHASE - WOQOD AL SALILIYAPS DOHA QA 0028999900 0513101450 000001260038 0513 011002#470"}]}