{"account_holder_address": "P.O.BOX 5498\nABU DHABI,ΑΕ\nAE", "account_holder_name": "MR ALAA E G HEJJI", "account_number": "143-100-3073983-01-9", "bank_currency": "AED", "closing_balance": 31633.03, "iban_number": "ΑΕ-76-035-143-100-3073983-01-9", "opening_balance": 32367.35, "page_number": 1.0, "statement_end_date": "05 NOV 2023", "statement_start_date": "01 SEP 2023", "total_credit_amount": 100326.59, "total_credit_transactions": 14.0, "total_debit_amount": 101060.91, "total_debit_transactions": 155.0, "transactions": [{"balance": 32367.35, "description": "Opening balance"}, {"balance": 23706.35, "debit": 8661.0, "description": "UADDS Cr Trf-501PY-71200001962022000023289000013", "transaction_date": "01 SEP 2023"}, {"balance": 19306.35, "debit": 4400.0, "description": "ATM Cash Withdrawal-FAB", "transaction_date": "02 SEP 2023"}, {"balance": 19326.94, "credit": 20.59, "description": "Debit Card Transaction-SHEIN Dubai", "transaction_date": "02 SEP 2023"}, {"balance": 43326.94, "credit": 24000.0, "description": "Salary Transfer-Salary Transfer from PARSONS INTERN", "transaction_date": "04 SEP 2023"}, {"balance": 43314.94, "debit": 12.0, "description": "Debit Card Transaction-AL GHAZAL TRANSPORT Abu Dhabi", "transaction_date": "04 SEP 2023"}, {"balance": 43302.94, "debit": 12.0, "description": "Debit Card Transaction-NATIONAL TAXI Abu Dhabi", "transaction_date": "04 SEP 2023"}, {"balance": 43237.94, "debit": 65.0, "description": "Debit Card Transaction-SAROUJA ROASTERY LLC ABU DHABI", "transaction_date": "04 SEP 2023"}, {"balance": 43220.04, "debit": 17.9, "description": "Debit Card Transaction-LULU HYPERMARKET- WTC ABU DHABI", "transaction_date": "04 SEP 2023"}, {"balance": 43128.81, "debit": 91.23, "description": "Debit Card Transaction-INSTANBUL FOODSTUFF Abu Dhabi", "transaction_date": "04 SEP 2023"}, {"balance": 43108.81, "debit": 20.0, "description": "Debit Card Transaction-ORGANIC FLOUR MILL Abu Dhabi", "transaction_date": "04 SEP 2023"}, {"balance": 43096.81, "debit": 12.0, "description": "Debit Card Transaction-TAWASUL TRANSPORT LLC Abu Dhabi", "transaction_date": "04 SEP 2023"}, {"balance": 43067.81, "debit": 29.0, "description": "Debit Card Transaction-Zaytooneh General Trad Abu", "transaction_date": "04 SEP 2023"}, {"balance": 42468.81, "debit": 599.0, "description": "Debit Card Transaction-LULU HYPERMARKET LLC B ABU DHABI", "transaction_date": "04 SEP 2023"}], "SearchablePDF": {"name": "FAB_Type_II_1.png_searchable.pdf", "url": "https://api.parseur.com/document/rAhac8OR.IYaoqV.qMtSMAsscDIht1p41Z84LSRBNGNUH-7wuNVFksM4xfB4ChFh/searchable_pdf/FAB_Type_II_1.png_searchable.pdf", "content_type": "application/pdf", "size": 243878}, "Template": null, "ParsingEngine": "AI"}